filehole/__init__.py
filehole-0.0.4.dist-info/LICENSE
filehole-0.0.4.dist-info/METADATA
filehole-0.0.4.dist-info/WHEEL
filehole-0.0.4.dist-info/top_level.txt
filehole-0.0.4.dist-info/RECORD
