Metadata-Version: 2.1
Name: filehole
Version: 0.0.4
Summary: Python library to find missing files in a scheduled delivery.
Author-email: Virginie Grosboillot <vestalisvirginis@gmail.com>
Project-URL: Homepage, https://github.com/vestalisvirginis/filehole
Project-URL: Bug Tracker, https://github.com/vestalisvirginis/filehole/issues
Classifier: Programming Language :: Python :: 3
Classifier: License :: OSI Approved :: MIT License
Classifier: Operating System :: OS Independent
Requires-Python: >=3.8
License-File: LICENSE
